solocompany/__init__.py
solocompany/address/__init__.py
solocompany/address/address.py
solocompany/address/department.py
solocompany/ai/__init__.py
solocompany/ai/llm/__init__.py
solocompany/ai/llm/chat.py
solocompany/ai/llm/text_to_image_prompt.py
solocompany/api/__init__.py
solocompany/api/lib/__init__.py
solocompany/api/lib/tab.py
solocompany/api/lib/view.py
solocompany/api/lib/web.py
solocompany/api/lib/window.py
solocompany/member/__init__.py
solocompany/member/chat.py
solocompany/member/chat_base.py
solocompany/member/history.py
solocompany/member/interrupt.py
solocompany/member/lib.py
solocompany/member/message.py
solocompany/member/prompt.jinja
solocompany/member/prompt.py
solocompany/reference/__init__.py
solocompany/reference/mcp.py
solocompany/reference/member.py
solocompany/reference/tool.py
solocompany/reference/workflow.py
solocompany/reference/lib/__init__.py
solocompany/reference/lib/call_func.py
solocompany/reference/lib/change_directory.py
solocompany/tool/__init__.py
solocompany/tool/tool_decorator.py
solocompany/ui/__init__.py
solocompany/ui/base.py
solocompany/ui/color.py
solocompany/ui/typ.py
solocompany/ui/ui_def.py
solocompany/utils/__init__.py
solocompany/utils/arg.py
solocompany/utils/env.py
solocompany/utils/json.py
solocompany/utils/process.py
solocompany/utils/socket.py
solocompany/utils/text_or_file.py
solocompany/utils/web.py
solocompany-0.0.91.dist-info/LICENSE
solocompany-0.0.91.dist-info/METADATA
solocompany-0.0.91.dist-info/WHEEL
solocompany-0.0.91.dist-info/top_level.txt
solocompany-0.0.91.dist-info/RECORD
