Metadata-Version: 2.1
Name: solocompany
Version: 0.0.91
Summary: Package for solocompany only!
Author: Jie Xiong
Author-email: 363692146@qq.com
Classifier: Programming Language :: Python :: 3
Classifier: Operating System :: OS Independent
Requires-Python: >=3.9
License-File: LICENSE
